altearnrpc/__init__.py
altearnrpc/__main__.py
altearnrpc/config.py
altearnrpc-0.1.5.dist-info/METADATA
altearnrpc-0.1.5.dist-info/WHEEL
altearnrpc-0.1.5.dist-info/entry_points.txt
altearnrpc-0.1.5.dist-info/top_level.txt
altearnrpc-0.1.5.dist-info/RECORD
